hproxy/__init__.py
hproxy/app.py
hproxy-0.1.2.dist-info/METADATA
hproxy-0.1.2.dist-info/WHEEL
hproxy-0.1.2.dist-info/entry_points.txt
hproxy-0.1.2.dist-info/top_level.txt
hproxy-0.1.2.dist-info/RECORD
