Metadata-Version: 2.2
Name: hproxy
Version: 0.1.2
Summary: A GUI tool for managing Kubernetes pod proxies
Home-page: https://github.com/yourusername/hproxy
Author: Your Name
Author-email: Your Name <your.email@example.com>
License: MIT
Project-URL: Homepage, https://github.com/yourusername/hproxy
Project-URL: Issues, https://github.com/yourusername/hproxy/issues
Classifier: Programming Language :: Python :: 3
Classifier: Programming Language :: Python :: 3.8
Classifier: Programming Language :: Python :: 3.9
Classifier: Programming Language :: Python :: 3.10
Classifier: Programming Language :: Python :: 3.11
Classifier: License :: OSI Approved :: MIT License
Classifier: Operating System :: OS Independent
Classifier: Development Status :: 4 - Beta
Classifier: Environment :: X11 Applications :: GTK
Classifier: Topic :: System :: Systems Administration
Requires-Python: >=3.8
Requires-Dist: kubernetes>=28.1.0
Requires-Dist: ttkthemes>=3.2.2
Requires-Dist: pillow>=10.0.0
